{
    "3exp": {
        "a1": 197581499528869.75,
        "b1": -0.03670156032366579,
        "a2": 157135933222195.75,
        "b2": -0.012012485290848376,
        "a3": 41597439178646.85,
        "b3": -0.004510881943207288,
        "t_hot": 221.6861386731369,
        "n_hot": 41597439178646.85,
        "start_index": 0,
        "end_index": 460,
        "a1_stdev": 8.587063417316868e+17,
        "b1_stdev": 193.66543290351535,
        "a2_stdev": 4.6920366238911366e+17,
        "b2_stdev": 24.40046880948016,
        "a3_stdev": 1.1695058566664286e+17,
        "b3_stdev": 3.5861783670050835,
        "t_hot_stdev": 176241.81807099882,
        "n_hot_stdev": 1.1695058566664286e+17
    },
    "2exp": null,
    "2nlsq": null,
    "1nlsq": null,
    "true_params": {
        "t_hot": 202.2083,
        "t_hot_stdev": 3.4866
    },
    "histogram": {
        "i": 1e+18,
        "l": 5.0,
        "a": 10.0,
        "filename": "hist_1e18_500_10"
    }
}